airena_game_client/__init__.py
airena_game_client/airena_game_client.py
airena_game_client/env.py
airena_game_client/py.typed
airena_game_client-0.1.0.dist-info/METADATA
airena_game_client-0.1.0.dist-info/WHEEL
airena_game_client-0.1.0.dist-info/RECORD
