Metadata-Version: 2.4
Name: airena-game-client
Version: 0.1.0
Summary: A Python client for interacting with the airena game API.
Project-URL: PyPI, https://pypi.org/project/airena-game-client/
Project-URL: GitHub, https://github.com/airena-dev/airena-python-game-client
Author-email: Henry Jones <henryivesjones@gmail.com>
Requires-Python: >=3.12
Requires-Dist: httpx>=0.28.1
Requires-Dist: pydantic-settings>=2.9.1
Requires-Dist: pydantic>=2.11.4
